<?xml version="1.0" encoding="UTF-8"?>
<rdf:RDF xmlns:rdf="http://www.w3.org/1999/02/22-rdf-syntax-ns#"
         xmlns:dc="http://purl.org/dc/elements/1.1/">
   <rdf:Description>
      <dc:title>The Tribes and Castes of the Central Provinces of India—Volume II</dc:title>
      <dc:creator>Robert Vane Russell (1873–1915)</dc:creator>
      <dc:creator>Rai Bahadur Hīra Lāl (1867–1934)</dc:creator>
      <dc:publisher>Project Gutenberg, Urbana, Illinois, USA., 2007-07-06</dc:publisher>
      <dc:date>2007-07-06</dc:date>
      <dc:rights>This eBook is for the use of anyone anywhere at no cost and with almost no restrictions whatsoever. You may copy it, give it away or re-use it under the terms of the Project Gutenberg License included with this eBook or online at www.gutenberg.org.

 This eBook is produced by Jeroen Hellingman and the Online Distributed Proofreading Team at www.pgdp.net from page images provided by the Million Books Project, supplemented with scans of the illustrations from original copies.

 

 Scans for this work are available from the Internet Archive (copy 1, 2, 3).

 </dc:rights>
      <dc:subject>Caste -- India -- Madhya Pradesh</dc:subject>
      <dc:subject>Ethnology -- India -- Madhya Pradesh</dc:subject>
      <dc:subject>Madhya Pradesh (India) -- Religion</dc:subject>
      <dc:subject>Madhya Pradesh (India) -- Scheduled tribes</dc:subject>
      <dc:identifier>pg:22010</dc:identifier>
   </rdf:Description>
</rdf:RDF>
